{
  "source": "CRFW_Media_Embeds.xlsx",
  "sheets": {
    "Bandcamp Releases": [
      {
        "Artist": "alphabets",
        "Title": "DDR",
        "Type": "album",
        "Release Date": "2011-11-06",
        "Bandcamp item_id": "4107832738",
        "# Tracks": 6,
        "Tracklist": "1. open / frog\n2. fish / jelly\n3. turtle / rainbow bee-eater\n4. gulls\n5. dolphin / shark\n6. seal / sandpipers",
        "Tags": null,
        "URL": "https://alphabets.bandcamp.com/album/ddr",
        "Artwork URL": "https://f4.bcbits.com/img/a1115283517_5.jpg",
        "Embed (iframe)": "<iframe style=\"border:0;width:100%;height:120px;\" src=\"https://bandcamp.com/EmbeddedPlayer/a=4107832738/size=small/bgcol=ffffff/linkcol=0687f5/artwork=small/transparent=true/\" seamless><a href=\"https://alphabets.bandcamp.com/album/ddr\">DDR, by alphabets</a></iframe>",
        "Notes": null
      },
      {
        "Artist": "alphabets",
        "Title": "play soundtrack",
        "Type": "album",
        "Release Date": "2011-11-10",
        "Bandcamp item_id": "2112966018",
        "# Tracks": 11,
        "Tracklist": "1. seating-open\n2. Ii-Iii\n3. Iii-Iiii\n4. interim I\n5. IIi\n6. IIi-Iii\n7. Iii-Iii\n8. IIiii-IIiv\n9. Interim II\n10. IIIi-IIIiv\n11. IIIiv-close",
        "Tags": null,
        "URL": "https://alphabets.bandcamp.com/album/play-soundtrack",
        "Artwork URL": "https://f4.bcbits.com/img/a2334446600_5.jpg",
        "Embed (iframe)": "<iframe style=\"border:0;width:100%;height:120px;\" src=\"https://bandcamp.com/EmbeddedPlayer/a=2112966018/size=small/bgcol=ffffff/linkcol=0687f5/artwork=small/transparent=true/\" seamless><a href=\"https://alphabets.bandcamp.com/album/play-soundtrack\">play soundtrack, by alphabets</a></iframe>",
        "Notes": null
      },
      {
        "Artist": "alphabets",
        "Title": "air mall",
        "Type": "track",
        "Release Date": "2012-01-03",
        "Bandcamp item_id": "2354364773",
        "# Tracks": 0,
        "Tracklist": null,
        "Tags": null,
        "URL": "https://alphabets.bandcamp.com/track/air-mall-3",
        "Artwork URL": "https://f4.bcbits.com/img/a2116726531_5.jpg",
        "Embed (iframe)": "<iframe style=\"border:0;width:100%;height:120px;\" src=\"https://bandcamp.com/EmbeddedPlayer/t=2354364773/size=small/bgcol=ffffff/linkcol=0687f5/artwork=small/transparent=true/\" seamless><a href=\"https://alphabets.bandcamp.com/track/air-mall-3\">air mall, by alphabets</a></iframe>",
        "Notes": null
      },
      {
        "Artist": "alphabets",
        "Title": "JEANJETS",
        "Type": "album",
        "Release Date": "2012-04-06",
        "Bandcamp item_id": "1914638874",
        "# Tracks": 6,
        "Tracklist": "1. GULFSTREAM IV\n2. DIAMONDII\n3. WULF TA 154 night fighter\n4. F22 RAPTOR\n5. 731 FALCON 20F\n6. ASTRA SP",
        "Tags": null,
        "URL": "https://alphabets.bandcamp.com/album/jeanjets",
        "Artwork URL": "https://f4.bcbits.com/img/a1835144587_5.jpg",
        "Embed (iframe)": "<iframe style=\"border:0;width:100%;height:120px;\" src=\"https://bandcamp.com/EmbeddedPlayer/a=1914638874/size=small/bgcol=ffffff/linkcol=0687f5/artwork=small/transparent=true/\" seamless><a href=\"https://alphabets.bandcamp.com/album/jeanjets\">JEANJETS, by alphabets</a></iframe>",
        "Notes": null
      },
      {
        "Artist": "alphabets",
        "Title": "antPAD",
        "Type": "album",
        "Release Date": "2012-04-20",
        "Bandcamp item_id": "1486312695",
        "# Tracks": 7,
        "Tracklist": "1. oceangun\n2. claw\n3. roomkey\n4. floor\n5. #treepunk\n6. see weed\n7. .rar uzi",
        "Tags": null,
        "URL": "https://alphabets.bandcamp.com/album/antpad",
        "Artwork URL": "https://f4.bcbits.com/img/a1645951658_5.jpg",
        "Embed (iframe)": "<iframe style=\"border:0;width:100%;height:120px;\" src=\"https://bandcamp.com/EmbeddedPlayer/a=1486312695/size=small/bgcol=ffffff/linkcol=0687f5/artwork=small/transparent=true/\" seamless><a href=\"https://alphabets.bandcamp.com/album/antpad\">antPAD, by alphabets</a></iframe>",
        "Notes": null
      },
      {
        "Artist": "alphabets",
        "Title": "DDR2/ HAUNTED",
        "Type": "album",
        "Release Date": "2012-05-18",
        "Bandcamp item_id": "1895348568",
        "# Tracks": 6,
        "Tracklist": "1. raptor signal.\n2. blood spill\n3. made u sick\n4. horror trax tha cycles\n5. st@rl!te hunnym00n\n6. dead haunter field. bludd in my i&#39;s.",
        "Tags": null,
        "URL": "https://alphabets.bandcamp.com/album/ddr2-haunted",
        "Artwork URL": "https://f4.bcbits.com/img/a2750018364_5.jpg",
        "Embed (iframe)": "<iframe style=\"border:0;width:100%;height:120px;\" src=\"https://bandcamp.com/EmbeddedPlayer/a=1895348568/size=small/bgcol=ffffff/linkcol=0687f5/artwork=small/transparent=true/\" seamless><a href=\"https://alphabets.bandcamp.com/album/ddr2-haunted\">DDR2/ HAUNTED, by alphabets</a></iframe>",
        "Notes": null
      },
      {
        "Artist": "alphabets",
        "Title": "SWEAT BEE: DANCE MIX",
        "Type": "album",
        "Release Date": "2012-07-17",
        "Bandcamp item_id": "524887154",
        "# Tracks": 5,
        "Tracklist": "1. i\n2. ii\n3. iii\n4. iv\n5. v",
        "Tags": null,
        "URL": "https://alphabets.bandcamp.com/album/sweat-bee-dance-mix",
        "Artwork URL": "https://f4.bcbits.com/img/a0351661414_5.jpg",
        "Embed (iframe)": "<iframe style=\"border:0;width:100%;height:120px;\" src=\"https://bandcamp.com/EmbeddedPlayer/a=524887154/size=small/bgcol=ffffff/linkcol=0687f5/artwork=small/transparent=true/\" seamless><a href=\"https://alphabets.bandcamp.com/album/sweat-bee-dance-mix\">SWEAT BEE: DANCE MIX, by alphabets</a></iframe>",
        "Notes": "2012 (per archive folder SWEATBEE_2012_[alphabets])"
      },
      {
        "Artist": "alphabets",
        "Title": "trapped in tha back of a jeep",
        "Type": "album",
        "Release Date": "2013-02-08",
        "Bandcamp item_id": "1166856439",
        "# Tracks": 7,
        "Tracklist": "1. wanter\n2. monster energy\n3. dog shades\n4. money drawing\n5. candles&amp;kimonos\n6. user\n7. trapped in tha back of a jeep",
        "Tags": null,
        "URL": "https://alphabets.bandcamp.com/album/trapped-in-tha-back-of-a-jeep",
        "Artwork URL": "https://f4.bcbits.com/img/a0295314916_5.jpg",
        "Embed (iframe)": "<iframe style=\"border:0;width:100%;height:120px;\" src=\"https://bandcamp.com/EmbeddedPlayer/a=1166856439/size=small/bgcol=ffffff/linkcol=0687f5/artwork=small/transparent=true/\" seamless><a href=\"https://alphabets.bandcamp.com/album/trapped-in-tha-back-of-a-jeep\">trapped in tha back of a jeep, by alphabets</a></iframe>",
        "Notes": "2013 (per archive folder trappedinthebackofajeep_2013_[alphabets])"
      },
      {
        "Artist": "alphabets",
        "Title": "400YEN",
        "Type": "album",
        "Release Date": "2013-03-04",
        "Bandcamp item_id": "2004946639",
        "# Tracks": 5,
        "Tracklist": "1. 400YEN\n2. on air silk tooth\n3. museum security\n4. hair pilot\n5. waver",
        "Tags": null,
        "URL": "https://alphabets.bandcamp.com/album/400yen",
        "Artwork URL": "https://f4.bcbits.com/img/a4069169954_5.jpg",
        "Embed (iframe)": "<iframe style=\"border:0;width:100%;height:120px;\" src=\"https://bandcamp.com/EmbeddedPlayer/a=2004946639/size=small/bgcol=ffffff/linkcol=0687f5/artwork=small/transparent=true/\" seamless><a href=\"https://alphabets.bandcamp.com/album/400yen\">400YEN, by alphabets</a></iframe>",
        "Notes": null
      },
      {
        "Artist": "alphabets",
        "Title": "ON CHAMPAGNE AND GREYHOUNDS",
        "Type": "album",
        "Release Date": "2013-11-07",
        "Bandcamp item_id": "1868665422",
        "# Tracks": 7,
        "Tracklist": "1. GEL STRIPPER\n2. SCENE GIRL HAIR SPRAYER\n3. AIRPORT STORE GIFTS\n4. LANDSCAPER\n5. GECKO RING\n6. SASHIMI IN THA TERMINAL\n7. STILL BORN, SHUT UP",
        "Tags": null,
        "URL": "https://alphabets.bandcamp.com/album/on-champagne-and-greyhounds-2",
        "Artwork URL": "https://f4.bcbits.com/img/a2550117726_5.jpg",
        "Embed (iframe)": "<iframe style=\"border:0;width:100%;height:120px;\" src=\"https://bandcamp.com/EmbeddedPlayer/a=1868665422/size=small/bgcol=ffffff/linkcol=0687f5/artwork=small/transparent=true/\" seamless><a href=\"https://alphabets.bandcamp.com/album/on-champagne-and-greyhounds-2\">ON CHAMPAGNE AND GREYHOUNDS, by alphabets</a></iframe>",
        "Notes": null
      },
      {
        "Artist": "alphabets",
        "Title": "SIBERIAN CHILL",
        "Type": "album",
        "Release Date": "2013-11-07",
        "Bandcamp item_id": "1350343704",
        "# Tracks": 8,
        "Tracklist": "1. SIBERIAN CHILL\n2. PAD THAI CUP\n3. ASTRAL PROJECTOR BLU RAZZ\n4. JADE LEAN\n5. DEAD CACTUS STEM\n6. THIEFF\n7. SPLIFF 2XX\n8. ICE CASTLE",
        "Tags": null,
        "URL": "https://alphabets.bandcamp.com/album/siberian-chill",
        "Artwork URL": "https://f4.bcbits.com/img/a2352291097_5.jpg",
        "Embed (iframe)": "<iframe style=\"border:0;width:100%;height:120px;\" src=\"https://bandcamp.com/EmbeddedPlayer/a=1350343704/size=small/bgcol=ffffff/linkcol=0687f5/artwork=small/transparent=true/\" seamless><a href=\"https://alphabets.bandcamp.com/album/siberian-chill\">SIBERIAN CHILL, by alphabets</a></iframe>",
        "Notes": null
      },
      {
        "Artist": "alphabets",
        "Title": "ANGRY BIRDS CHAINS",
        "Type": "album",
        "Release Date": "2013-11-07",
        "Bandcamp item_id": "109723474",
        "# Tracks": 1,
        "Tracklist": "1. ANGRY BIRDS CHAINS",
        "Tags": null,
        "URL": "https://alphabets.bandcamp.com/album/angry-birds-chains",
        "Artwork URL": "https://f4.bcbits.com/img/a2806882182_5.jpg",
        "Embed (iframe)": "<iframe style=\"border:0;width:100%;height:120px;\" src=\"https://bandcamp.com/EmbeddedPlayer/a=109723474/size=small/bgcol=ffffff/linkcol=0687f5/artwork=small/transparent=true/\" seamless><a href=\"https://alphabets.bandcamp.com/album/angry-birds-chains\">ANGRY BIRDS CHAINS, by alphabets</a></iframe>",
        "Notes": null
      },
      {
        "Artist": "alphabets",
        "Title": "CAVE RAVE",
        "Type": "album",
        "Release Date": "2013-11-07",
        "Bandcamp item_id": "3567709956",
        "# Tracks": 9,
        "Tracklist": "1. running with snowshoes\n2. not my house but it was\n3. CAT TATS\n4. RADIO FREE EGYPT\n5. sci - fi moan stars\n6. SNAKE LADY\n7. DINO\n8. CAVE RAVE\n9. gospel doctor",
        "Tags": null,
        "URL": "https://alphabets.bandcamp.com/album/cave-rave",
        "Artwork URL": "https://f4.bcbits.com/img/a0194743088_5.jpg",
        "Embed (iframe)": "<iframe style=\"border:0;width:100%;height:120px;\" src=\"https://bandcamp.com/EmbeddedPlayer/a=3567709956/size=small/bgcol=ffffff/linkcol=0687f5/artwork=small/transparent=true/\" seamless><a href=\"https://alphabets.bandcamp.com/album/cave-rave\">CAVE RAVE, by alphabets</a></iframe>",
        "Notes": null
      },
      {
        "Artist": "alphabets",
        "Title": "BIEBER JERBOA",
        "Type": "album",
        "Release Date": "2013-11-07",
        "Bandcamp item_id": "3575767379",
        "# Tracks": 9,
        "Tracklist": "1. GEL PENS 2010\n2. BRAIN WAVES DANCE HALL\n3. DREAM LIFE inter missiles\n4. %%2 zoom out\n5. DEM ON YA k pep\n6. toy lemurs\n7. aah real monsters\n8. CHEREE (suicide cover)\n9. LET GO OF STRESS",
        "Tags": null,
        "URL": "https://alphabets.bandcamp.com/album/bieber-jerboa",
        "Artwork URL": "https://f4.bcbits.com/img/a4063927109_5.jpg",
        "Embed (iframe)": "<iframe style=\"border:0;width:100%;height:120px;\" src=\"https://bandcamp.com/EmbeddedPlayer/a=3575767379/size=small/bgcol=ffffff/linkcol=0687f5/artwork=small/transparent=true/\" seamless><a href=\"https://alphabets.bandcamp.com/album/bieber-jerboa\">BIEBER JERBOA, by alphabets</a></iframe>",
        "Notes": "2010 (per archive folder BIEBER JERBOA_2010_[phonebooks]; Bandcamp upload 2013-11-07)"
      },
      {
        "Artist": "alphabets",
        "Title": "611",
        "Type": "album",
        "Release Date": "2013-11-07",
        "Bandcamp item_id": "144101403",
        "# Tracks": 10,
        "Tracklist": "1. 999 stat ups\n2. cub 3\n3. do spells\n4. where R those wolves\n5. porch level\n6. turtle stair\n7. jay low\n8. dryad\n9. high lite saber\n10. tequila backpack",
        "Tags": null,
        "URL": "https://alphabets.bandcamp.com/album/611",
        "Artwork URL": "https://f4.bcbits.com/img/a2435121029_5.jpg",
        "Embed (iframe)": "<iframe style=\"border:0;width:100%;height:120px;\" src=\"https://bandcamp.com/EmbeddedPlayer/a=144101403/size=small/bgcol=ffffff/linkcol=0687f5/artwork=small/transparent=true/\" seamless><a href=\"https://alphabets.bandcamp.com/album/611\">611, by alphabets</a></iframe>",
        "Notes": null
      },
      {
        "Artist": "alphabets",
        "Title": "THRU THA RIP",
        "Type": "album",
        "Release Date": "2013-12-13",
        "Bandcamp item_id": "3295825815",
        "# Tracks": 13,
        "Tracklist": "1. THEORY OF THA GAME\n2. TROPICAL SEX IN MY HEAD\n3. FINE CHINA\n4. LEMON SLICES IN MY CUP\n5. RAPTOR JAZZ\n6. NASTY FUTURE\n7. HACK THA CULTURE\n8. SNOW HABIT\n9. A R T I L E C T\n10. EVIAN SPRAY\n11. LOSE CONTROL\n12. HYENA CRISTAL\n13. FROG EATER",
        "Tags": null,
        "URL": "https://alphabets.bandcamp.com/album/thru-tha-rip",
        "Artwork URL": "https://f4.bcbits.com/img/a3452735138_5.jpg",
        "Embed (iframe)": "<iframe style=\"border:0;width:100%;height:120px;\" src=\"https://bandcamp.com/EmbeddedPlayer/a=3295825815/size=small/bgcol=ffffff/linkcol=0687f5/artwork=small/transparent=true/\" seamless><a href=\"https://alphabets.bandcamp.com/album/thru-tha-rip\">THRU THA RIP, by alphabets</a></iframe>",
        "Notes": null
      },
      {
        "Artist": "killd by",
        "Title": "Court Clothes",
        "Type": "album",
        "Release Date": "2015-09-17",
        "Bandcamp item_id": "3159341709",
        "# Tracks": 14,
        "Tracklist": "1. butterFly eFFecT\n2. hopeless [222]\n3. *e*v*i*L_*a*n*g*eLz*\n4. COPE_\n5. birD_jaiL\n6. thunder*_stoned*\n7. *L*i*g*h*t*&amp;*Acid*\n8. FLAG_burn**\n9. generation-zebra\n10. _no_decision_\n11. *G*e*n*i*e_CluB\n12. __gong-water\n13. *river_inside_\n14. *L*a*p*s*e*",
        "Tags": null,
        "URL": "https://killdby.bandcamp.com/album/court-clothes",
        "Artwork URL": "https://f4.bcbits.com/img/a3398758399_5.jpg",
        "Embed (iframe)": "<iframe style=\"border:0;width:100%;height:120px;\" src=\"https://bandcamp.com/EmbeddedPlayer/a=3159341709/size=small/bgcol=ffffff/linkcol=0687f5/artwork=small/transparent=true/\" seamless><a href=\"https://killdby.bandcamp.com/album/court-clothes\">Court Clothes, by killd by</a></iframe>",
        "Notes": null
      },
      {
        "Artist": "killd by",
        "Title": "Recovery",
        "Type": "album",
        "Release Date": "2015-09-17",
        "Bandcamp item_id": "1808675884",
        "# Tracks": 16,
        "Tracklist": "1. Like a PeLiCaN\n2. SHAPE SHIFTER\n3. can&#39;t stand sTiLL\n4. True Communication\n5. Zentai\n6. on FLy\n7. No Energy Vamp\n8. afterlife on Loop\n9. Tekno Cheetah\n10. cameras in my body\n11. Mind ControL\n12. seX wiTh lightning\n13. in the throw\n14. issues\n15. out of Your Head\n16. no memory S.W.I.M.",
        "Tags": null,
        "URL": "https://killdby.bandcamp.com/album/recovery",
        "Artwork URL": "https://f4.bcbits.com/img/a3640137374_5.jpg",
        "Embed (iframe)": "<iframe style=\"border:0;width:100%;height:120px;\" src=\"https://bandcamp.com/EmbeddedPlayer/a=1808675884/size=small/bgcol=ffffff/linkcol=0687f5/artwork=small/transparent=true/\" seamless><a href=\"https://killdby.bandcamp.com/album/recovery\">Recovery, by killd by</a></iframe>",
        "Notes": null
      },
      {
        "Artist": "killd by",
        "Title": "DJpooLsiDe vol.1",
        "Type": "album",
        "Release Date": "2015-11-24",
        "Bandcamp item_id": "4283738485",
        "# Tracks": 20,
        "Tracklist": "1. x1x\n2. x2x\n3. x3x\n4. x4x\n5. x5x\n6. x6x\n7. x7x\n8. x8x\n9. x9x\n10. x10x\n11. x11x\n12. x12x\n13. x13x\n14. x14x\n15. x15x\n16. x16x\n17. x17x\n18. x18x\n19. x19x\n20. x20x",
        "Tags": null,
        "URL": "https://killdby.bandcamp.com/album/djpoolside-vol-1",
        "Artwork URL": "https://f4.bcbits.com/img/a3387338327_5.jpg",
        "Embed (iframe)": "<iframe style=\"border:0;width:100%;height:120px;\" src=\"https://bandcamp.com/EmbeddedPlayer/a=4283738485/size=small/bgcol=ffffff/linkcol=0687f5/artwork=small/transparent=true/\" seamless><a href=\"https://killdby.bandcamp.com/album/djpoolside-vol-1\">DJpooLsiDe vol.1, by killd by</a></iframe>",
        "Notes": null
      },
      {
        "Artist": "killd by",
        "Title": "uya-050",
        "Type": "album",
        "Release Date": "2016-09-22",
        "Bandcamp item_id": "3025882557",
        "# Tracks": 1,
        "Tracklist": "1. uya-050",
        "Tags": null,
        "URL": "https://killdby.bandcamp.com/album/uya-050",
        "Artwork URL": "https://f4.bcbits.com/img/a2693322209_5.jpg",
        "Embed (iframe)": "<iframe style=\"border:0;width:100%;height:120px;\" src=\"https://bandcamp.com/EmbeddedPlayer/a=3025882557/size=small/bgcol=ffffff/linkcol=0687f5/artwork=small/transparent=true/\" seamless><a href=\"https://killdby.bandcamp.com/album/uya-050\">uya-050, by killd by</a></iframe>",
        "Notes": null
      },
      {
        "Artist": "killd by",
        "Title": "draw blood",
        "Type": "track",
        "Release Date": "2016-09-22",
        "Bandcamp item_id": "4171893740",
        "# Tracks": 0,
        "Tracklist": null,
        "Tags": null,
        "URL": "https://killdby.bandcamp.com/track/draw-blood",
        "Artwork URL": "https://f4.bcbits.com/img/a1843885642_5.jpg",
        "Embed (iframe)": "<iframe style=\"border:0;width:100%;height:120px;\" src=\"https://bandcamp.com/EmbeddedPlayer/t=4171893740/size=small/bgcol=ffffff/linkcol=0687f5/artwork=small/transparent=true/\" seamless><a href=\"https://killdby.bandcamp.com/track/draw-blood\">draw blood, by killd by</a></iframe>",
        "Notes": null
      },
      {
        "Artist": "killd by",
        "Title": "P22",
        "Type": "album",
        "Release Date": "2016-09-25",
        "Bandcamp item_id": "1815870025",
        "# Tracks": 6,
        "Tracklist": "1. 310uu\n2. apt 311\n3. apt11ii\n4. apt314\n5. apt312\n6. apt313",
        "Tags": null,
        "URL": "https://killdby.bandcamp.com/album/p22",
        "Artwork URL": "https://f4.bcbits.com/img/a2360568146_5.jpg",
        "Embed (iframe)": "<iframe style=\"border:0;width:100%;height:120px;\" src=\"https://bandcamp.com/EmbeddedPlayer/a=1815870025/size=small/bgcol=ffffff/linkcol=0687f5/artwork=small/transparent=true/\" seamless><a href=\"https://killdby.bandcamp.com/album/p22\">P22, by killd by</a></iframe>",
        "Notes": null
      },
      {
        "Artist": "killd by",
        "Title": "Carolina Reaper",
        "Type": "album",
        "Release Date": "2016-10-21",
        "Bandcamp item_id": "1435868671",
        "# Tracks": 1,
        "Tracklist": "1. Carolina Reaper",
        "Tags": null,
        "URL": "https://killdby.bandcamp.com/album/carolina-reaper",
        "Artwork URL": "https://f4.bcbits.com/img/a1523611994_5.jpg",
        "Embed (iframe)": "<iframe style=\"border:0;width:100%;height:120px;\" src=\"https://bandcamp.com/EmbeddedPlayer/a=1435868671/size=small/bgcol=ffffff/linkcol=0687f5/artwork=small/transparent=true/\" seamless><a href=\"https://killdby.bandcamp.com/album/carolina-reaper\">Carolina Reaper, by killd by</a></iframe>",
        "Notes": null
      },
      {
        "Artist": "killd by",
        "Title": "DDR3:Loaner phone",
        "Type": "album",
        "Release Date": "2016-11-03",
        "Bandcamp item_id": "2467959500",
        "# Tracks": 23,
        "Tracklist": "1. bust the skilz\n2. cut the music2\n3. DanceFloorPPLdropz\n4. danceMCHN\n5. DDrev\n6. Djps2tropicParadise\n7. energyVamp&amp;Djps1\n8. extc\n9. UhOhSay\n10. LemonCupRMX\n11. iMissUrLoveRMXpetria\n12. no superstar dropz\n13. onlevel\n14. pom\n15. lonely ppL\n16. sociaLmediaDropz\n17. surge\n18. synth2\n19. thisJayZ\n20. u got the luv rmx\n21. way2do It\n22. worldVocal stretch\n23. Z100YourOwnMovie",
        "Tags": null,
        "URL": "https://killdby.bandcamp.com/album/ddr3-loaner-phone",
        "Artwork URL": "https://f4.bcbits.com/img/a1325985707_5.jpg",
        "Embed (iframe)": "<iframe style=\"border:0;width:100%;height:120px;\" src=\"https://bandcamp.com/EmbeddedPlayer/a=2467959500/size=small/bgcol=ffffff/linkcol=0687f5/artwork=small/transparent=true/\" seamless><a href=\"https://killdby.bandcamp.com/album/ddr3-loaner-phone\">DDR3:Loaner phone, by killd by</a></iframe>",
        "Notes": null
      },
      {
        "Artist": "killd by",
        "Title": "2014-2016 [Bsides]",
        "Type": "album",
        "Release Date": "2016-12-31",
        "Bandcamp item_id": "3614340002",
        "# Tracks": 20,
        "Tracklist": "1. SWIM\n2. tha GoodLife 2xxx\n3. captivity\n4. lulz nrg [physical&amp;mental]\n5. no haiku\n6. on fly 1\n7. CSS1\n8. SHAPE SHIFTR1\n9. rain HuLa\n10. Last Animal\n11. kiss over glass\n12. Call You\n13. show me love [ Robin S. remix ]\n14. ez bb\n15. Leave Pompeii\n16. heLL\n17. saywut now turn up\n18. jongo\n19. Million Dollr app\n20. psy-traiL",
        "Tags": null,
        "URL": "https://killdby.bandcamp.com/album/2014-2016-bsides",
        "Artwork URL": "https://f4.bcbits.com/img/a2758950999_5.jpg",
        "Embed (iframe)": "<iframe style=\"border:0;width:100%;height:120px;\" src=\"https://bandcamp.com/EmbeddedPlayer/a=3614340002/size=small/bgcol=ffffff/linkcol=0687f5/artwork=small/transparent=true/\" seamless><a href=\"https://killdby.bandcamp.com/album/2014-2016-bsides\">2014-2016 [Bsides], by killd by</a></iframe>",
        "Notes": null
      },
      {
        "Artist": "killd by",
        "Title": "EMT",
        "Type": "album",
        "Release Date": "2017-02-12",
        "Bandcamp item_id": "1496420930",
        "# Tracks": 1,
        "Tracklist": "1. EMT",
        "Tags": null,
        "URL": "https://killdby.bandcamp.com/album/emt",
        "Artwork URL": "https://f4.bcbits.com/img/a3723546282_5.jpg",
        "Embed (iframe)": "<iframe style=\"border:0;width:100%;height:120px;\" src=\"https://bandcamp.com/EmbeddedPlayer/a=1496420930/size=small/bgcol=ffffff/linkcol=0687f5/artwork=small/transparent=true/\" seamless><a href=\"https://killdby.bandcamp.com/album/emt\">EMT, by killd by</a></iframe>",
        "Notes": null
      }
    ],
    "YouTube Videos": [
      {
        "Channel": "Colin Ward (@colinrfw)",
        "Title": "CAKE2",
        "Video ID": "G-cJgp3W6kM",
        "Published": "13 years ago",
        "Duration": "43 seconds",
        "Views": "255 views",
        "Description": null,
        "URL": "https://www.youtube.com/watch?v=G-cJgp3W6kM",
        "Embed (iframe)": "<iframe width=\"560\" height=\"315\" src=\"https://www.youtube.com/embed/G-cJgp3W6kM\" frameborder=\"0\" allowfullscreen></iframe>",
        "Notes": null
      },
      {
        "Channel": "Colin Ward (@colinrfw)",
        "Title": "CAKE",
        "Video ID": "y70y9QnqGDI",
        "Published": "13 years ago",
        "Duration": "16 seconds",
        "Views": "396 views",
        "Description": null,
        "URL": "https://www.youtube.com/watch?v=y70y9QnqGDI",
        "Embed (iframe)": "<iframe width=\"560\" height=\"315\" src=\"https://www.youtube.com/embed/y70y9QnqGDI\" frameborder=\"0\" allowfullscreen></iframe>",
        "Notes": null
      },
      {
        "Channel": "Colin Ward (@colinrfw)",
        "Title": "bushwicks finest barber shop",
        "Video ID": "4Wlqk8kY8b8",
        "Published": "13 years ago",
        "Duration": "2 minutes, 26 seconds",
        "Views": "159 views",
        "Description": null,
        "URL": "https://www.youtube.com/watch?v=4Wlqk8kY8b8",
        "Embed (iframe)": "<iframe width=\"560\" height=\"315\" src=\"https://www.youtube.com/embed/4Wlqk8kY8b8\" frameborder=\"0\" allowfullscreen></iframe>",
        "Notes": null
      },
      {
        "Channel": "Colin Ward (@colinrfw)",
        "Title": "pictureplane/alphabets budget rental truck mini tour",
        "Video ID": "rivWQMlxCfY",
        "Published": "13 years ago",
        "Duration": "18 minutes, 57 seconds",
        "Views": "504 views",
        "Description": null,
        "URL": "https://www.youtube.com/watch?v=rivWQMlxCfY",
        "Embed (iframe)": "<iframe width=\"560\" height=\"315\" src=\"https://www.youtube.com/embed/rivWQMlxCfY\" frameborder=\"0\" allowfullscreen></iframe>",
        "Notes": null
      },
      {
        "Channel": "Colin Ward (@colinrfw)",
        "Title": "tokkin chit.3gp",
        "Video ID": "Zb_Z35jhC58",
        "Published": "13 years ago",
        "Duration": "4 minutes, 6 seconds",
        "Views": "140 views",
        "Description": null,
        "URL": "https://www.youtube.com/watch?v=Zb_Z35jhC58",
        "Embed (iframe)": "<iframe width=\"560\" height=\"315\" src=\"https://www.youtube.com/embed/Zb_Z35jhC58\" frameborder=\"0\" allowfullscreen></iframe>",
        "Notes": null
      },
      {
        "Channel": "Colin Ward (@colinrfw)",
        "Title": "bobby shiftwell 1",
        "Video ID": "qglJag9VqS0",
        "Published": "13 years ago",
        "Duration": "3 minutes, 14 seconds",
        "Views": "92 views",
        "Description": null,
        "URL": "https://www.youtube.com/watch?v=qglJag9VqS0",
        "Embed (iframe)": "<iframe width=\"560\" height=\"315\" src=\"https://www.youtube.com/embed/qglJag9VqS0\" frameborder=\"0\" allowfullscreen></iframe>",
        "Notes": null
      },
      {
        "Channel": "Colin Ward (@colinrfw)",
        "Title": "Squirrel world",
        "Video ID": "rw_6qiymrnw",
        "Published": "13 years ago",
        "Duration": "1 minute, 28 seconds",
        "Views": "53 views",
        "Description": null,
        "URL": "https://www.youtube.com/watch?v=rw_6qiymrnw",
        "Embed (iframe)": "<iframe width=\"560\" height=\"315\" src=\"https://www.youtube.com/embed/rw_6qiymrnw\" frameborder=\"0\" allowfullscreen></iframe>",
        "Notes": null
      },
      {
        "Channel": "Colin Ward (@colinrfw)",
        "Title": "umbrella poppers",
        "Video ID": "1qqjbd_gjzI",
        "Published": "13 years ago",
        "Duration": "4 minutes, 44 seconds",
        "Views": "280 views",
        "Description": null,
        "URL": "https://www.youtube.com/watch?v=1qqjbd_gjzI",
        "Embed (iframe)": "<iframe width=\"560\" height=\"315\" src=\"https://www.youtube.com/embed/1qqjbd_gjzI\" frameborder=\"0\" allowfullscreen></iframe>",
        "Notes": null
      },
      {
        "Channel": "Colin Ward (@colinrfw)",
        "Title": "BOX COLLECTORS",
        "Video ID": "pIWrYBTW_h4",
        "Published": "13 years ago",
        "Duration": "4 minutes, 28 seconds",
        "Views": "135 views",
        "Description": null,
        "URL": "https://www.youtube.com/watch?v=pIWrYBTW_h4",
        "Embed (iframe)": "<iframe width=\"560\" height=\"315\" src=\"https://www.youtube.com/embed/pIWrYBTW_h4\" frameborder=\"0\" allowfullscreen></iframe>",
        "Notes": null
      },
      {
        "Channel": "Colin Ward (@colinrfw)",
        "Title": "if u see somebody hatin point em out",
        "Video ID": "ih-NdK83okw",
        "Published": "14 years ago",
        "Duration": "18 seconds",
        "Views": "129 views",
        "Description": null,
        "URL": "https://www.youtube.com/watch?v=ih-NdK83okw",
        "Embed (iframe)": "<iframe width=\"560\" height=\"315\" src=\"https://www.youtube.com/embed/ih-NdK83okw\" frameborder=\"0\" allowfullscreen></iframe>",
        "Notes": null
      },
      {
        "Channel": "Colin Ward (@colinrfw)",
        "Title": "DTTD.mov",
        "Video ID": "fWYIWVFvJyk",
        "Published": "14 years ago",
        "Duration": "2 minutes, 49 seconds",
        "Views": "427 views",
        "Description": null,
        "URL": "https://www.youtube.com/watch?v=fWYIWVFvJyk",
        "Embed (iframe)": "<iframe width=\"560\" height=\"315\" src=\"https://www.youtube.com/embed/fWYIWVFvJyk\" frameborder=\"0\" allowfullscreen></iframe>",
        "Notes": null
      },
      {
        "Channel": "Colin Ward (@colinrfw)",
        "Title": "merkaba",
        "Video ID": "PO-mJjjcdig",
        "Published": "14 years ago",
        "Duration": "25 seconds",
        "Views": "65 views",
        "Description": null,
        "URL": "https://www.youtube.com/watch?v=PO-mJjjcdig",
        "Embed (iframe)": "<iframe width=\"560\" height=\"315\" src=\"https://www.youtube.com/embed/PO-mJjjcdig\" frameborder=\"0\" allowfullscreen></iframe>",
        "Notes": null
      },
      {
        "Channel": "Colin Ward (@colinrfw)",
        "Title": "piano marsh",
        "Video ID": "1RV75ykdA8o",
        "Published": "14 years ago",
        "Duration": "1 minute, 38 seconds",
        "Views": "51 views",
        "Description": null,
        "URL": "https://www.youtube.com/watch?v=1RV75ykdA8o",
        "Embed (iframe)": "<iframe width=\"560\" height=\"315\" src=\"https://www.youtube.com/embed/1RV75ykdA8o\" frameborder=\"0\" allowfullscreen></iframe>",
        "Notes": null
      },
      {
        "Channel": "Colin Ward (@colinrfw)",
        "Title": "forest tube",
        "Video ID": "yHtnEIjt7wU",
        "Published": "14 years ago",
        "Duration": "1 minute, 9 seconds",
        "Views": "162 views",
        "Description": null,
        "URL": "https://www.youtube.com/watch?v=yHtnEIjt7wU",
        "Embed (iframe)": "<iframe width=\"560\" height=\"315\" src=\"https://www.youtube.com/embed/yHtnEIjt7wU\" frameborder=\"0\" allowfullscreen></iframe>",
        "Notes": null
      },
      {
        "Channel": "Colin Ward (@colinrfw)",
        "Title": "$word $oup 3",
        "Video ID": "VCL4az61ACQ",
        "Published": "14 years ago",
        "Duration": "27 seconds",
        "Views": "53 views",
        "Description": null,
        "URL": "https://www.youtube.com/watch?v=VCL4az61ACQ",
        "Embed (iframe)": "<iframe width=\"560\" height=\"315\" src=\"https://www.youtube.com/embed/VCL4az61ACQ\" frameborder=\"0\" allowfullscreen></iframe>",
        "Notes": null
      },
      {
        "Channel": "Colin Ward (@colinrfw)",
        "Title": "jan9 16st drumming 3",
        "Video ID": "lyoqoBgXBUQ",
        "Published": "14 years ago",
        "Duration": "1 minute, 21 seconds",
        "Views": "225 views",
        "Description": null,
        "URL": "https://www.youtube.com/watch?v=lyoqoBgXBUQ",
        "Embed (iframe)": "<iframe width=\"560\" height=\"315\" src=\"https://www.youtube.com/embed/lyoqoBgXBUQ\" frameborder=\"0\" allowfullscreen></iframe>",
        "Notes": null
      },
      {
        "Channel": "Colin Ward (@colinrfw)",
        "Title": "happy holidays",
        "Video ID": "shR8xrD4m14",
        "Published": "14 years ago",
        "Duration": "55 seconds",
        "Views": "56 views",
        "Description": null,
        "URL": "https://www.youtube.com/watch?v=shR8xrD4m14",
        "Embed (iframe)": "<iframe width=\"560\" height=\"315\" src=\"https://www.youtube.com/embed/shR8xrD4m14\" frameborder=\"0\" allowfullscreen></iframe>",
        "Notes": null
      },
      {
        "Channel": "Colin Ward (@colinrfw)",
        "Title": "Meow dunk surfing",
        "Video ID": "HpbdpdfKRjU",
        "Published": "14 years ago",
        "Duration": "1 minute, 29 seconds",
        "Views": "93 views",
        "Description": null,
        "URL": "https://www.youtube.com/watch?v=HpbdpdfKRjU",
        "Embed (iframe)": "<iframe width=\"560\" height=\"315\" src=\"https://www.youtube.com/embed/HpbdpdfKRjU\" frameborder=\"0\" allowfullscreen></iframe>",
        "Notes": null
      },
      {
        "Channel": "Colin Ward (@colinrfw)",
        "Title": "prokofieff violin theme in variations on marimba",
        "Video ID": "3U5f4XC5jUs",
        "Published": "14 years ago",
        "Duration": "3 minutes, 47 seconds",
        "Views": "353 views",
        "Description": null,
        "URL": "https://www.youtube.com/watch?v=3U5f4XC5jUs",
        "Embed (iframe)": "<iframe width=\"560\" height=\"315\" src=\"https://www.youtube.com/embed/3U5f4XC5jUs\" frameborder=\"0\" allowfullscreen></iframe>",
        "Notes": null
      },
      {
        "Channel": "Colin Ward (@colinrfw)",
        "Title": "Mtv cribs",
        "Video ID": "iYbZXUVYVoY",
        "Published": "14 years ago",
        "Duration": "1 minute, 8 seconds",
        "Views": "55 views",
        "Description": null,
        "URL": "https://www.youtube.com/watch?v=iYbZXUVYVoY",
        "Embed (iframe)": "<iframe width=\"560\" height=\"315\" src=\"https://www.youtube.com/embed/iYbZXUVYVoY\" frameborder=\"0\" allowfullscreen></iframe>",
        "Notes": null
      },
      {
        "Channel": "Colin Ward (@colinrfw)",
        "Title": "Sword soup",
        "Video ID": "IN3FB09bw2o",
        "Published": "14 years ago",
        "Duration": "1 minute, 11 seconds",
        "Views": "84 views",
        "Description": null,
        "URL": "https://www.youtube.com/watch?v=IN3FB09bw2o",
        "Embed (iframe)": "<iframe width=\"560\" height=\"315\" src=\"https://www.youtube.com/embed/IN3FB09bw2o\" frameborder=\"0\" allowfullscreen></iframe>",
        "Notes": null
      },
      {
        "Channel": "Colin Ward (@colinrfw)",
        "Title": "google fox news debate question.mov",
        "Video ID": "RNJeldaVdZU",
        "Published": "14 years ago",
        "Duration": "3 minutes, 18 seconds",
        "Views": "272 views",
        "Description": null,
        "URL": "https://www.youtube.com/watch?v=RNJeldaVdZU",
        "Embed (iframe)": "<iframe width=\"560\" height=\"315\" src=\"https://www.youtube.com/embed/RNJeldaVdZU\" frameborder=\"0\" allowfullscreen></iframe>",
        "Notes": null
      },
      {
        "Channel": "Colin Ward (@colinrfw)",
        "Title": "and eat it too.mov",
        "Video ID": "gMA50VW5h74",
        "Published": "14 years ago",
        "Duration": "49 seconds",
        "Views": "103 views",
        "Description": null,
        "URL": "https://www.youtube.com/watch?v=gMA50VW5h74",
        "Embed (iframe)": "<iframe width=\"560\" height=\"315\" src=\"https://www.youtube.com/embed/gMA50VW5h74\" frameborder=\"0\" allowfullscreen></iframe>",
        "Notes": null
      },
      {
        "Channel": "Colin Ward (@colinrfw)",
        "Title": "virtual reality.mov",
        "Video ID": "KvHeV2_fTRo",
        "Published": "14 years ago",
        "Duration": "1 minute, 6 seconds",
        "Views": "242 views",
        "Description": null,
        "URL": "https://www.youtube.com/watch?v=KvHeV2_fTRo",
        "Embed (iframe)": "<iframe width=\"560\" height=\"315\" src=\"https://www.youtube.com/embed/KvHeV2_fTRo\" frameborder=\"0\" allowfullscreen></iframe>",
        "Notes": null
      },
      {
        "Channel": "Colin Ward (@colinrfw)",
        "Title": "take me to the wine beach.mov",
        "Video ID": "YcNjn7IJiWY",
        "Published": "14 years ago",
        "Duration": "2 minutes, 29 seconds",
        "Views": "713 views",
        "Description": null,
        "URL": "https://www.youtube.com/watch?v=YcNjn7IJiWY",
        "Embed (iframe)": "<iframe width=\"560\" height=\"315\" src=\"https://www.youtube.com/embed/YcNjn7IJiWY\" frameborder=\"0\" allowfullscreen></iframe>",
        "Notes": null
      },
      {
        "Channel": "Colin Ward (@colinrfw)",
        "Title": "Sting",
        "Video ID": "Z7hR_LUg6PA",
        "Published": "14 years ago",
        "Duration": "49 seconds",
        "Views": "45 views",
        "Description": null,
        "URL": "https://www.youtube.com/watch?v=Z7hR_LUg6PA",
        "Embed (iframe)": "<iframe width=\"560\" height=\"315\" src=\"https://www.youtube.com/embed/Z7hR_LUg6PA\" frameborder=\"0\" allowfullscreen></iframe>",
        "Notes": null
      },
      {
        "Channel": "Colin Ward (@colinrfw)",
        "Title": "street drumming summer 2011",
        "Video ID": "MGLhUMVTwbk",
        "Published": "14 years ago",
        "Duration": "5 minutes, 14 seconds",
        "Views": "263 views",
        "Description": null,
        "URL": "https://www.youtube.com/watch?v=MGLhUMVTwbk",
        "Embed (iframe)": "<iframe width=\"560\" height=\"315\" src=\"https://www.youtube.com/embed/MGLhUMVTwbk\" frameborder=\"0\" allowfullscreen></iframe>",
        "Notes": null
      },
      {
        "Channel": "Colin Ward (@colinrfw)",
        "Title": "Hang wid meee",
        "Video ID": "i3eSUH4PxDI",
        "Published": "14 years ago",
        "Duration": "53 seconds",
        "Views": "211 views",
        "Description": null,
        "URL": "https://www.youtube.com/watch?v=i3eSUH4PxDI",
        "Embed (iframe)": "<iframe width=\"560\" height=\"315\" src=\"https://www.youtube.com/embed/i3eSUH4PxDI\" frameborder=\"0\" allowfullscreen></iframe>",
        "Notes": null
      },
      {
        "Channel": "Colin Ward (@colinrfw)",
        "Title": "How to love",
        "Video ID": "2Pdy85P4Lm8",
        "Published": "14 years ago",
        "Duration": "1 minute, 4 seconds",
        "Views": "40 views",
        "Description": null,
        "URL": "https://www.youtube.com/watch?v=2Pdy85P4Lm8",
        "Embed (iframe)": "<iframe width=\"560\" height=\"315\" src=\"https://www.youtube.com/embed/2Pdy85P4Lm8\" frameborder=\"0\" allowfullscreen></iframe>",
        "Notes": null
      },
      {
        "Channel": "Colin Ward (@colinrfw)",
        "Title": "Castle thing",
        "Video ID": "TkNeIghoxrA",
        "Published": "14 years ago",
        "Duration": "1 minute, 4 seconds",
        "Views": "44 views",
        "Description": null,
        "URL": "https://www.youtube.com/watch?v=TkNeIghoxrA",
        "Embed (iframe)": "<iframe width=\"560\" height=\"315\" src=\"https://www.youtube.com/embed/TkNeIghoxrA\" frameborder=\"0\" allowfullscreen></iframe>",
        "Notes": null
      },
      {
        "Channel": "Luke Thinnes",
        "Title": "Alphabets - Live On Denver Open Media 2011",
        "Video ID": "h_LBkFxlzOc",
        "Published": "2019-10-03",
        "Duration": null,
        "Views": "273",
        "Description": "Colin Ward and Stephan Herrera perform as Alphabets on Denver Open Media in April of 2011. In loving memory of Colin Ward, 8/29/1990 - 1/31/2018.",
        "URL": "https://www.youtube.com/watch?v=h_LBkFxlzOc",
        "Embed (iframe)": "<iframe width=\"560\" height=\"315\" src=\"https://www.youtube.com/embed/h_LBkFxlzOc\" frameborder=\"0\" allowfullscreen></iframe>",
        "Notes": "Tribute / additional context"
      },
      {
        "Channel": "B-side Archive (Obscure Music \\u0026 Lost Media)",
        "Title": "alphabets - dec09SCIFI (FULL ALBUM) [2009]",
        "Video ID": "MqUB_DSUvNw",
        "Published": "2022-06-25",
        "Duration": null,
        "Views": "13",
        "Description": "https://alphabets.bandcamp.com/album/dec09scifi alphabets was an experimental, glitchy, electronic noise project from 2008-2013 by colin ward 00:00 - phets 02:38 - adoorabellz 04:37 - palace parade fevers forever 06:41 - robodogs nighttime cage howls 07:57 - builders inventors 10:36 - chrome stuff 1",
        "URL": "https://www.youtube.com/watch?v=MqUB_DSUvNw",
        "Embed (iframe)": "<iframe width=\"560\" height=\"315\" src=\"https://www.youtube.com/embed/MqUB_DSUvNw\" frameborder=\"0\" allowfullscreen></iframe>",
        "Notes": "Tribute / additional context"
      }
    ],
    "SoundCloud Tracks": [
      {
        "Type": "profile",
        "Title": "Killd By",
        "Track ID": null,
        "User ID": "1540445",
        "Upload Date": null,
        "Description": "inquiries colinrfw@gmail.com www.killdby.bandcamp.com formerly alphabets www.alphabets.bandcamp.com <3",
        "URL": "https://soundcloud.com/killdby",
        "Artwork URL": "https://i1.sndcdn.com/avatars-000340501653-fsq5f6-t500x500.jpg",
        "Embed (iframe)": "<iframe width=\"100%\" height=\"166\" scrolling=\"no\" frameborder=\"no\" allow=\"autoplay\" src=\"https://w.soundcloud.com/player/?url=https://soundcloud.com/killdby&color=%23ff5500&auto_play=false&hide_related=false&show_comments=true&show_user=true&show_reposts=false&show_teaser=true\"></iframe>"
      },
      {
        "Type": "track",
        "Title": "Dedication - For Colin Ward",
        "Track ID": "395543691",
        "User ID": "6313978",
        "Upload Date": null,
        "Description": "https://killdby.bandcamp.com | https://alphabets.bandcamp.com DONATE --> https://www.crfw.art --- Absorbing Colin’s musical output intensely over the past few days. I’m so grateful that he was so",
        "URL": "https://soundcloud.com/thug-entrancer/dedication-for-colin-ward",
        "Artwork URL": "https://i1.sndcdn.com/artworks-000298372965-vkcqpt-t500x500.jpg",
        "Embed (iframe)": "<iframe width=\"100%\" height=\"166\" scrolling=\"no\" frameborder=\"no\" allow=\"autoplay\" src=\"https://w.soundcloud.com/player/?url=https://soundcloud.com/thug-entrancer/dedication-for-colin-ward&color=%23ff5500&auto_play=false&hide_related=false&show_comments=true&show_user=true&show_reposts=false&show_teaser=true\"></iframe>"
      }
    ],
    "All Media (flat)": [
      {
        "Source": "Bandcamp",
        "Artist/Channel": "alphabets",
        "Title": "DDR",
        "Type": "album",
        "Date": "2011-11-06",
        "Platform ID": "4107832738",
        "URL": "https://alphabets.bandcamp.com/album/ddr",
        "Embed (iframe)": "<iframe style=\"border:0;width:100%;height:120px;\" src=\"https://bandcamp.com/EmbeddedPlayer/a=4107832738/size=small/bgcol=ffffff/linkcol=0687f5/artwork=small/transparent=true/\" seamless></iframe>"
      },
      {
        "Source": "Bandcamp",
        "Artist/Channel": "alphabets",
        "Title": "play soundtrack",
        "Type": "album",
        "Date": "2011-11-10",
        "Platform ID": "2112966018",
        "URL": "https://alphabets.bandcamp.com/album/play-soundtrack",
        "Embed (iframe)": "<iframe style=\"border:0;width:100%;height:120px;\" src=\"https://bandcamp.com/EmbeddedPlayer/a=2112966018/size=small/bgcol=ffffff/linkcol=0687f5/artwork=small/transparent=true/\" seamless></iframe>"
      },
      {
        "Source": "Bandcamp",
        "Artist/Channel": "alphabets",
        "Title": "air mall",
        "Type": "track",
        "Date": "2012-01-03",
        "Platform ID": "2354364773",
        "URL": "https://alphabets.bandcamp.com/track/air-mall-3",
        "Embed (iframe)": "<iframe style=\"border:0;width:100%;height:120px;\" src=\"https://bandcamp.com/EmbeddedPlayer/t=2354364773/size=small/bgcol=ffffff/linkcol=0687f5/artwork=small/transparent=true/\" seamless></iframe>"
      },
      {
        "Source": "Bandcamp",
        "Artist/Channel": "alphabets",
        "Title": "JEANJETS",
        "Type": "album",
        "Date": "2012-04-06",
        "Platform ID": "1914638874",
        "URL": "https://alphabets.bandcamp.com/album/jeanjets",
        "Embed (iframe)": "<iframe style=\"border:0;width:100%;height:120px;\" src=\"https://bandcamp.com/EmbeddedPlayer/a=1914638874/size=small/bgcol=ffffff/linkcol=0687f5/artwork=small/transparent=true/\" seamless></iframe>"
      },
      {
        "Source": "Bandcamp",
        "Artist/Channel": "alphabets",
        "Title": "antPAD",
        "Type": "album",
        "Date": "2012-04-20",
        "Platform ID": "1486312695",
        "URL": "https://alphabets.bandcamp.com/album/antpad",
        "Embed (iframe)": "<iframe style=\"border:0;width:100%;height:120px;\" src=\"https://bandcamp.com/EmbeddedPlayer/a=1486312695/size=small/bgcol=ffffff/linkcol=0687f5/artwork=small/transparent=true/\" seamless></iframe>"
      },
      {
        "Source": "Bandcamp",
        "Artist/Channel": "alphabets",
        "Title": "DDR2/ HAUNTED",
        "Type": "album",
        "Date": "2012-05-18",
        "Platform ID": "1895348568",
        "URL": "https://alphabets.bandcamp.com/album/ddr2-haunted",
        "Embed (iframe)": "<iframe style=\"border:0;width:100%;height:120px;\" src=\"https://bandcamp.com/EmbeddedPlayer/a=1895348568/size=small/bgcol=ffffff/linkcol=0687f5/artwork=small/transparent=true/\" seamless></iframe>"
      },
      {
        "Source": "Bandcamp",
        "Artist/Channel": "alphabets",
        "Title": "SWEAT BEE: DANCE MIX",
        "Type": "album",
        "Date": "2012-07-17",
        "Platform ID": "524887154",
        "URL": "https://alphabets.bandcamp.com/album/sweat-bee-dance-mix",
        "Embed (iframe)": "<iframe style=\"border:0;width:100%;height:120px;\" src=\"https://bandcamp.com/EmbeddedPlayer/a=524887154/size=small/bgcol=ffffff/linkcol=0687f5/artwork=small/transparent=true/\" seamless></iframe>"
      },
      {
        "Source": "Bandcamp",
        "Artist/Channel": "alphabets",
        "Title": "trapped in tha back of a jeep",
        "Type": "album",
        "Date": "2013-02-08",
        "Platform ID": "1166856439",
        "URL": "https://alphabets.bandcamp.com/album/trapped-in-tha-back-of-a-jeep",
        "Embed (iframe)": "<iframe style=\"border:0;width:100%;height:120px;\" src=\"https://bandcamp.com/EmbeddedPlayer/a=1166856439/size=small/bgcol=ffffff/linkcol=0687f5/artwork=small/transparent=true/\" seamless></iframe>"
      },
      {
        "Source": "Bandcamp",
        "Artist/Channel": "alphabets",
        "Title": "400YEN",
        "Type": "album",
        "Date": "2013-03-04",
        "Platform ID": "2004946639",
        "URL": "https://alphabets.bandcamp.com/album/400yen",
        "Embed (iframe)": "<iframe style=\"border:0;width:100%;height:120px;\" src=\"https://bandcamp.com/EmbeddedPlayer/a=2004946639/size=small/bgcol=ffffff/linkcol=0687f5/artwork=small/transparent=true/\" seamless></iframe>"
      },
      {
        "Source": "Bandcamp",
        "Artist/Channel": "alphabets",
        "Title": "ON CHAMPAGNE AND GREYHOUNDS",
        "Type": "album",
        "Date": "2013-11-07",
        "Platform ID": "1868665422",
        "URL": "https://alphabets.bandcamp.com/album/on-champagne-and-greyhounds-2",
        "Embed (iframe)": "<iframe style=\"border:0;width:100%;height:120px;\" src=\"https://bandcamp.com/EmbeddedPlayer/a=1868665422/size=small/bgcol=ffffff/linkcol=0687f5/artwork=small/transparent=true/\" seamless></iframe>"
      },
      {
        "Source": "Bandcamp",
        "Artist/Channel": "alphabets",
        "Title": "SIBERIAN CHILL",
        "Type": "album",
        "Date": "2013-11-07",
        "Platform ID": "1350343704",
        "URL": "https://alphabets.bandcamp.com/album/siberian-chill",
        "Embed (iframe)": "<iframe style=\"border:0;width:100%;height:120px;\" src=\"https://bandcamp.com/EmbeddedPlayer/a=1350343704/size=small/bgcol=ffffff/linkcol=0687f5/artwork=small/transparent=true/\" seamless></iframe>"
      },
      {
        "Source": "Bandcamp",
        "Artist/Channel": "alphabets",
        "Title": "ANGRY BIRDS CHAINS",
        "Type": "album",
        "Date": "2013-11-07",
        "Platform ID": "109723474",
        "URL": "https://alphabets.bandcamp.com/album/angry-birds-chains",
        "Embed (iframe)": "<iframe style=\"border:0;width:100%;height:120px;\" src=\"https://bandcamp.com/EmbeddedPlayer/a=109723474/size=small/bgcol=ffffff/linkcol=0687f5/artwork=small/transparent=true/\" seamless></iframe>"
      },
      {
        "Source": "Bandcamp",
        "Artist/Channel": "alphabets",
        "Title": "CAVE RAVE",
        "Type": "album",
        "Date": "2013-11-07",
        "Platform ID": "3567709956",
        "URL": "https://alphabets.bandcamp.com/album/cave-rave",
        "Embed (iframe)": "<iframe style=\"border:0;width:100%;height:120px;\" src=\"https://bandcamp.com/EmbeddedPlayer/a=3567709956/size=small/bgcol=ffffff/linkcol=0687f5/artwork=small/transparent=true/\" seamless></iframe>"
      },
      {
        "Source": "Bandcamp",
        "Artist/Channel": "alphabets",
        "Title": "BIEBER JERBOA",
        "Type": "album",
        "Date": "2013-11-07",
        "Platform ID": "3575767379",
        "URL": "https://alphabets.bandcamp.com/album/bieber-jerboa",
        "Embed (iframe)": "<iframe style=\"border:0;width:100%;height:120px;\" src=\"https://bandcamp.com/EmbeddedPlayer/a=3575767379/size=small/bgcol=ffffff/linkcol=0687f5/artwork=small/transparent=true/\" seamless></iframe>"
      },
      {
        "Source": "Bandcamp",
        "Artist/Channel": "alphabets",
        "Title": "611",
        "Type": "album",
        "Date": "2013-11-07",
        "Platform ID": "144101403",
        "URL": "https://alphabets.bandcamp.com/album/611",
        "Embed (iframe)": "<iframe style=\"border:0;width:100%;height:120px;\" src=\"https://bandcamp.com/EmbeddedPlayer/a=144101403/size=small/bgcol=ffffff/linkcol=0687f5/artwork=small/transparent=true/\" seamless></iframe>"
      },
      {
        "Source": "Bandcamp",
        "Artist/Channel": "alphabets",
        "Title": "THRU THA RIP",
        "Type": "album",
        "Date": "2013-12-13",
        "Platform ID": "3295825815",
        "URL": "https://alphabets.bandcamp.com/album/thru-tha-rip",
        "Embed (iframe)": "<iframe style=\"border:0;width:100%;height:120px;\" src=\"https://bandcamp.com/EmbeddedPlayer/a=3295825815/size=small/bgcol=ffffff/linkcol=0687f5/artwork=small/transparent=true/\" seamless></iframe>"
      },
      {
        "Source": "Bandcamp",
        "Artist/Channel": "killd by",
        "Title": "Court Clothes",
        "Type": "album",
        "Date": "2015-09-17",
        "Platform ID": "3159341709",
        "URL": "https://killdby.bandcamp.com/album/court-clothes",
        "Embed (iframe)": "<iframe style=\"border:0;width:100%;height:120px;\" src=\"https://bandcamp.com/EmbeddedPlayer/a=3159341709/size=small/bgcol=ffffff/linkcol=0687f5/artwork=small/transparent=true/\" seamless></iframe>"
      },
      {
        "Source": "Bandcamp",
        "Artist/Channel": "killd by",
        "Title": "Recovery",
        "Type": "album",
        "Date": "2015-09-17",
        "Platform ID": "1808675884",
        "URL": "https://killdby.bandcamp.com/album/recovery",
        "Embed (iframe)": "<iframe style=\"border:0;width:100%;height:120px;\" src=\"https://bandcamp.com/EmbeddedPlayer/a=1808675884/size=small/bgcol=ffffff/linkcol=0687f5/artwork=small/transparent=true/\" seamless></iframe>"
      },
      {
        "Source": "Bandcamp",
        "Artist/Channel": "killd by",
        "Title": "DJpooLsiDe vol.1",
        "Type": "album",
        "Date": "2015-11-24",
        "Platform ID": "4283738485",
        "URL": "https://killdby.bandcamp.com/album/djpoolside-vol-1",
        "Embed (iframe)": "<iframe style=\"border:0;width:100%;height:120px;\" src=\"https://bandcamp.com/EmbeddedPlayer/a=4283738485/size=small/bgcol=ffffff/linkcol=0687f5/artwork=small/transparent=true/\" seamless></iframe>"
      },
      {
        "Source": "Bandcamp",
        "Artist/Channel": "killd by",
        "Title": "uya-050",
        "Type": "album",
        "Date": "2016-09-22",
        "Platform ID": "3025882557",
        "URL": "https://killdby.bandcamp.com/album/uya-050",
        "Embed (iframe)": "<iframe style=\"border:0;width:100%;height:120px;\" src=\"https://bandcamp.com/EmbeddedPlayer/a=3025882557/size=small/bgcol=ffffff/linkcol=0687f5/artwork=small/transparent=true/\" seamless></iframe>"
      },
      {
        "Source": "Bandcamp",
        "Artist/Channel": "killd by",
        "Title": "draw blood",
        "Type": "track",
        "Date": "2016-09-22",
        "Platform ID": "4171893740",
        "URL": "https://killdby.bandcamp.com/track/draw-blood",
        "Embed (iframe)": "<iframe style=\"border:0;width:100%;height:120px;\" src=\"https://bandcamp.com/EmbeddedPlayer/t=4171893740/size=small/bgcol=ffffff/linkcol=0687f5/artwork=small/transparent=true/\" seamless></iframe>"
      },
      {
        "Source": "Bandcamp",
        "Artist/Channel": "killd by",
        "Title": "P22",
        "Type": "album",
        "Date": "2016-09-25",
        "Platform ID": "1815870025",
        "URL": "https://killdby.bandcamp.com/album/p22",
        "Embed (iframe)": "<iframe style=\"border:0;width:100%;height:120px;\" src=\"https://bandcamp.com/EmbeddedPlayer/a=1815870025/size=small/bgcol=ffffff/linkcol=0687f5/artwork=small/transparent=true/\" seamless></iframe>"
      },
      {
        "Source": "Bandcamp",
        "Artist/Channel": "killd by",
        "Title": "Carolina Reaper",
        "Type": "album",
        "Date": "2016-10-21",
        "Platform ID": "1435868671",
        "URL": "https://killdby.bandcamp.com/album/carolina-reaper",
        "Embed (iframe)": "<iframe style=\"border:0;width:100%;height:120px;\" src=\"https://bandcamp.com/EmbeddedPlayer/a=1435868671/size=small/bgcol=ffffff/linkcol=0687f5/artwork=small/transparent=true/\" seamless></iframe>"
      },
      {
        "Source": "Bandcamp",
        "Artist/Channel": "killd by",
        "Title": "DDR3:Loaner phone",
        "Type": "album",
        "Date": "2016-11-03",
        "Platform ID": "2467959500",
        "URL": "https://killdby.bandcamp.com/album/ddr3-loaner-phone",
        "Embed (iframe)": "<iframe style=\"border:0;width:100%;height:120px;\" src=\"https://bandcamp.com/EmbeddedPlayer/a=2467959500/size=small/bgcol=ffffff/linkcol=0687f5/artwork=small/transparent=true/\" seamless></iframe>"
      },
      {
        "Source": "Bandcamp",
        "Artist/Channel": "killd by",
        "Title": "2014-2016 [Bsides]",
        "Type": "album",
        "Date": "2016-12-31",
        "Platform ID": "3614340002",
        "URL": "https://killdby.bandcamp.com/album/2014-2016-bsides",
        "Embed (iframe)": "<iframe style=\"border:0;width:100%;height:120px;\" src=\"https://bandcamp.com/EmbeddedPlayer/a=3614340002/size=small/bgcol=ffffff/linkcol=0687f5/artwork=small/transparent=true/\" seamless></iframe>"
      },
      {
        "Source": "Bandcamp",
        "Artist/Channel": "killd by",
        "Title": "EMT",
        "Type": "album",
        "Date": "2017-02-12",
        "Platform ID": "1496420930",
        "URL": "https://killdby.bandcamp.com/album/emt",
        "Embed (iframe)": "<iframe style=\"border:0;width:100%;height:120px;\" src=\"https://bandcamp.com/EmbeddedPlayer/a=1496420930/size=small/bgcol=ffffff/linkcol=0687f5/artwork=small/transparent=true/\" seamless></iframe>"
      },
      {
        "Source": "YouTube",
        "Artist/Channel": "Colin Ward (@colinrfw)",
        "Title": "CAKE2",
        "Type": "video",
        "Date": "13 years ago",
        "Platform ID": "G-cJgp3W6kM",
        "URL": "https://www.youtube.com/watch?v=G-cJgp3W6kM",
        "Embed (iframe)": "<iframe width=\"560\" height=\"315\" src=\"https://www.youtube.com/embed/G-cJgp3W6kM\" frameborder=\"0\" allowfullscreen></iframe>"
      },
      {
        "Source": "YouTube",
        "Artist/Channel": "Colin Ward (@colinrfw)",
        "Title": "CAKE",
        "Type": "video",
        "Date": "13 years ago",
        "Platform ID": "y70y9QnqGDI",
        "URL": "https://www.youtube.com/watch?v=y70y9QnqGDI",
        "Embed (iframe)": "<iframe width=\"560\" height=\"315\" src=\"https://www.youtube.com/embed/y70y9QnqGDI\" frameborder=\"0\" allowfullscreen></iframe>"
      },
      {
        "Source": "YouTube",
        "Artist/Channel": "Colin Ward (@colinrfw)",
        "Title": "bushwicks finest barber shop",
        "Type": "video",
        "Date": "13 years ago",
        "Platform ID": "4Wlqk8kY8b8",
        "URL": "https://www.youtube.com/watch?v=4Wlqk8kY8b8",
        "Embed (iframe)": "<iframe width=\"560\" height=\"315\" src=\"https://www.youtube.com/embed/4Wlqk8kY8b8\" frameborder=\"0\" allowfullscreen></iframe>"
      },
      {
        "Source": "YouTube",
        "Artist/Channel": "Colin Ward (@colinrfw)",
        "Title": "pictureplane/alphabets budget rental truck mini tour",
        "Type": "video",
        "Date": "13 years ago",
        "Platform ID": "rivWQMlxCfY",
        "URL": "https://www.youtube.com/watch?v=rivWQMlxCfY",
        "Embed (iframe)": "<iframe width=\"560\" height=\"315\" src=\"https://www.youtube.com/embed/rivWQMlxCfY\" frameborder=\"0\" allowfullscreen></iframe>"
      },
      {
        "Source": "YouTube",
        "Artist/Channel": "Colin Ward (@colinrfw)",
        "Title": "tokkin chit.3gp",
        "Type": "video",
        "Date": "13 years ago",
        "Platform ID": "Zb_Z35jhC58",
        "URL": "https://www.youtube.com/watch?v=Zb_Z35jhC58",
        "Embed (iframe)": "<iframe width=\"560\" height=\"315\" src=\"https://www.youtube.com/embed/Zb_Z35jhC58\" frameborder=\"0\" allowfullscreen></iframe>"
      },
      {
        "Source": "YouTube",
        "Artist/Channel": "Colin Ward (@colinrfw)",
        "Title": "bobby shiftwell 1",
        "Type": "video",
        "Date": "13 years ago",
        "Platform ID": "qglJag9VqS0",
        "URL": "https://www.youtube.com/watch?v=qglJag9VqS0",
        "Embed (iframe)": "<iframe width=\"560\" height=\"315\" src=\"https://www.youtube.com/embed/qglJag9VqS0\" frameborder=\"0\" allowfullscreen></iframe>"
      },
      {
        "Source": "YouTube",
        "Artist/Channel": "Colin Ward (@colinrfw)",
        "Title": "Squirrel world",
        "Type": "video",
        "Date": "13 years ago",
        "Platform ID": "rw_6qiymrnw",
        "URL": "https://www.youtube.com/watch?v=rw_6qiymrnw",
        "Embed (iframe)": "<iframe width=\"560\" height=\"315\" src=\"https://www.youtube.com/embed/rw_6qiymrnw\" frameborder=\"0\" allowfullscreen></iframe>"
      },
      {
        "Source": "YouTube",
        "Artist/Channel": "Colin Ward (@colinrfw)",
        "Title": "umbrella poppers",
        "Type": "video",
        "Date": "13 years ago",
        "Platform ID": "1qqjbd_gjzI",
        "URL": "https://www.youtube.com/watch?v=1qqjbd_gjzI",
        "Embed (iframe)": "<iframe width=\"560\" height=\"315\" src=\"https://www.youtube.com/embed/1qqjbd_gjzI\" frameborder=\"0\" allowfullscreen></iframe>"
      },
      {
        "Source": "YouTube",
        "Artist/Channel": "Colin Ward (@colinrfw)",
        "Title": "BOX COLLECTORS",
        "Type": "video",
        "Date": "13 years ago",
        "Platform ID": "pIWrYBTW_h4",
        "URL": "https://www.youtube.com/watch?v=pIWrYBTW_h4",
        "Embed (iframe)": "<iframe width=\"560\" height=\"315\" src=\"https://www.youtube.com/embed/pIWrYBTW_h4\" frameborder=\"0\" allowfullscreen></iframe>"
      },
      {
        "Source": "YouTube",
        "Artist/Channel": "Colin Ward (@colinrfw)",
        "Title": "if u see somebody hatin point em out",
        "Type": "video",
        "Date": "14 years ago",
        "Platform ID": "ih-NdK83okw",
        "URL": "https://www.youtube.com/watch?v=ih-NdK83okw",
        "Embed (iframe)": "<iframe width=\"560\" height=\"315\" src=\"https://www.youtube.com/embed/ih-NdK83okw\" frameborder=\"0\" allowfullscreen></iframe>"
      },
      {
        "Source": "YouTube",
        "Artist/Channel": "Colin Ward (@colinrfw)",
        "Title": "DTTD.mov",
        "Type": "video",
        "Date": "14 years ago",
        "Platform ID": "fWYIWVFvJyk",
        "URL": "https://www.youtube.com/watch?v=fWYIWVFvJyk",
        "Embed (iframe)": "<iframe width=\"560\" height=\"315\" src=\"https://www.youtube.com/embed/fWYIWVFvJyk\" frameborder=\"0\" allowfullscreen></iframe>"
      },
      {
        "Source": "YouTube",
        "Artist/Channel": "Colin Ward (@colinrfw)",
        "Title": "merkaba",
        "Type": "video",
        "Date": "14 years ago",
        "Platform ID": "PO-mJjjcdig",
        "URL": "https://www.youtube.com/watch?v=PO-mJjjcdig",
        "Embed (iframe)": "<iframe width=\"560\" height=\"315\" src=\"https://www.youtube.com/embed/PO-mJjjcdig\" frameborder=\"0\" allowfullscreen></iframe>"
      },
      {
        "Source": "YouTube",
        "Artist/Channel": "Colin Ward (@colinrfw)",
        "Title": "piano marsh",
        "Type": "video",
        "Date": "14 years ago",
        "Platform ID": "1RV75ykdA8o",
        "URL": "https://www.youtube.com/watch?v=1RV75ykdA8o",
        "Embed (iframe)": "<iframe width=\"560\" height=\"315\" src=\"https://www.youtube.com/embed/1RV75ykdA8o\" frameborder=\"0\" allowfullscreen></iframe>"
      },
      {
        "Source": "YouTube",
        "Artist/Channel": "Colin Ward (@colinrfw)",
        "Title": "forest tube",
        "Type": "video",
        "Date": "14 years ago",
        "Platform ID": "yHtnEIjt7wU",
        "URL": "https://www.youtube.com/watch?v=yHtnEIjt7wU",
        "Embed (iframe)": "<iframe width=\"560\" height=\"315\" src=\"https://www.youtube.com/embed/yHtnEIjt7wU\" frameborder=\"0\" allowfullscreen></iframe>"
      },
      {
        "Source": "YouTube",
        "Artist/Channel": "Colin Ward (@colinrfw)",
        "Title": "$word $oup 3",
        "Type": "video",
        "Date": "14 years ago",
        "Platform ID": "VCL4az61ACQ",
        "URL": "https://www.youtube.com/watch?v=VCL4az61ACQ",
        "Embed (iframe)": "<iframe width=\"560\" height=\"315\" src=\"https://www.youtube.com/embed/VCL4az61ACQ\" frameborder=\"0\" allowfullscreen></iframe>"
      },
      {
        "Source": "YouTube",
        "Artist/Channel": "Colin Ward (@colinrfw)",
        "Title": "jan9 16st drumming 3",
        "Type": "video",
        "Date": "14 years ago",
        "Platform ID": "lyoqoBgXBUQ",
        "URL": "https://www.youtube.com/watch?v=lyoqoBgXBUQ",
        "Embed (iframe)": "<iframe width=\"560\" height=\"315\" src=\"https://www.youtube.com/embed/lyoqoBgXBUQ\" frameborder=\"0\" allowfullscreen></iframe>"
      },
      {
        "Source": "YouTube",
        "Artist/Channel": "Colin Ward (@colinrfw)",
        "Title": "happy holidays",
        "Type": "video",
        "Date": "14 years ago",
        "Platform ID": "shR8xrD4m14",
        "URL": "https://www.youtube.com/watch?v=shR8xrD4m14",
        "Embed (iframe)": "<iframe width=\"560\" height=\"315\" src=\"https://www.youtube.com/embed/shR8xrD4m14\" frameborder=\"0\" allowfullscreen></iframe>"
      },
      {
        "Source": "YouTube",
        "Artist/Channel": "Colin Ward (@colinrfw)",
        "Title": "Meow dunk surfing",
        "Type": "video",
        "Date": "14 years ago",
        "Platform ID": "HpbdpdfKRjU",
        "URL": "https://www.youtube.com/watch?v=HpbdpdfKRjU",
        "Embed (iframe)": "<iframe width=\"560\" height=\"315\" src=\"https://www.youtube.com/embed/HpbdpdfKRjU\" frameborder=\"0\" allowfullscreen></iframe>"
      },
      {
        "Source": "YouTube",
        "Artist/Channel": "Colin Ward (@colinrfw)",
        "Title": "prokofieff violin theme in variations on marimba",
        "Type": "video",
        "Date": "14 years ago",
        "Platform ID": "3U5f4XC5jUs",
        "URL": "https://www.youtube.com/watch?v=3U5f4XC5jUs",
        "Embed (iframe)": "<iframe width=\"560\" height=\"315\" src=\"https://www.youtube.com/embed/3U5f4XC5jUs\" frameborder=\"0\" allowfullscreen></iframe>"
      },
      {
        "Source": "YouTube",
        "Artist/Channel": "Colin Ward (@colinrfw)",
        "Title": "Mtv cribs",
        "Type": "video",
        "Date": "14 years ago",
        "Platform ID": "iYbZXUVYVoY",
        "URL": "https://www.youtube.com/watch?v=iYbZXUVYVoY",
        "Embed (iframe)": "<iframe width=\"560\" height=\"315\" src=\"https://www.youtube.com/embed/iYbZXUVYVoY\" frameborder=\"0\" allowfullscreen></iframe>"
      },
      {
        "Source": "YouTube",
        "Artist/Channel": "Colin Ward (@colinrfw)",
        "Title": "Sword soup",
        "Type": "video",
        "Date": "14 years ago",
        "Platform ID": "IN3FB09bw2o",
        "URL": "https://www.youtube.com/watch?v=IN3FB09bw2o",
        "Embed (iframe)": "<iframe width=\"560\" height=\"315\" src=\"https://www.youtube.com/embed/IN3FB09bw2o\" frameborder=\"0\" allowfullscreen></iframe>"
      },
      {
        "Source": "YouTube",
        "Artist/Channel": "Colin Ward (@colinrfw)",
        "Title": "google fox news debate question.mov",
        "Type": "video",
        "Date": "14 years ago",
        "Platform ID": "RNJeldaVdZU",
        "URL": "https://www.youtube.com/watch?v=RNJeldaVdZU",
        "Embed (iframe)": "<iframe width=\"560\" height=\"315\" src=\"https://www.youtube.com/embed/RNJeldaVdZU\" frameborder=\"0\" allowfullscreen></iframe>"
      },
      {
        "Source": "YouTube",
        "Artist/Channel": "Colin Ward (@colinrfw)",
        "Title": "and eat it too.mov",
        "Type": "video",
        "Date": "14 years ago",
        "Platform ID": "gMA50VW5h74",
        "URL": "https://www.youtube.com/watch?v=gMA50VW5h74",
        "Embed (iframe)": "<iframe width=\"560\" height=\"315\" src=\"https://www.youtube.com/embed/gMA50VW5h74\" frameborder=\"0\" allowfullscreen></iframe>"
      },
      {
        "Source": "YouTube",
        "Artist/Channel": "Colin Ward (@colinrfw)",
        "Title": "virtual reality.mov",
        "Type": "video",
        "Date": "14 years ago",
        "Platform ID": "KvHeV2_fTRo",
        "URL": "https://www.youtube.com/watch?v=KvHeV2_fTRo",
        "Embed (iframe)": "<iframe width=\"560\" height=\"315\" src=\"https://www.youtube.com/embed/KvHeV2_fTRo\" frameborder=\"0\" allowfullscreen></iframe>"
      },
      {
        "Source": "YouTube",
        "Artist/Channel": "Colin Ward (@colinrfw)",
        "Title": "take me to the wine beach.mov",
        "Type": "video",
        "Date": "14 years ago",
        "Platform ID": "YcNjn7IJiWY",
        "URL": "https://www.youtube.com/watch?v=YcNjn7IJiWY",
        "Embed (iframe)": "<iframe width=\"560\" height=\"315\" src=\"https://www.youtube.com/embed/YcNjn7IJiWY\" frameborder=\"0\" allowfullscreen></iframe>"
      },
      {
        "Source": "YouTube",
        "Artist/Channel": "Colin Ward (@colinrfw)",
        "Title": "Sting",
        "Type": "video",
        "Date": "14 years ago",
        "Platform ID": "Z7hR_LUg6PA",
        "URL": "https://www.youtube.com/watch?v=Z7hR_LUg6PA",
        "Embed (iframe)": "<iframe width=\"560\" height=\"315\" src=\"https://www.youtube.com/embed/Z7hR_LUg6PA\" frameborder=\"0\" allowfullscreen></iframe>"
      },
      {
        "Source": "YouTube",
        "Artist/Channel": "Colin Ward (@colinrfw)",
        "Title": "street drumming summer 2011",
        "Type": "video",
        "Date": "14 years ago",
        "Platform ID": "MGLhUMVTwbk",
        "URL": "https://www.youtube.com/watch?v=MGLhUMVTwbk",
        "Embed (iframe)": "<iframe width=\"560\" height=\"315\" src=\"https://www.youtube.com/embed/MGLhUMVTwbk\" frameborder=\"0\" allowfullscreen></iframe>"
      },
      {
        "Source": "YouTube",
        "Artist/Channel": "Colin Ward (@colinrfw)",
        "Title": "Hang wid meee",
        "Type": "video",
        "Date": "14 years ago",
        "Platform ID": "i3eSUH4PxDI",
        "URL": "https://www.youtube.com/watch?v=i3eSUH4PxDI",
        "Embed (iframe)": "<iframe width=\"560\" height=\"315\" src=\"https://www.youtube.com/embed/i3eSUH4PxDI\" frameborder=\"0\" allowfullscreen></iframe>"
      },
      {
        "Source": "YouTube",
        "Artist/Channel": "Colin Ward (@colinrfw)",
        "Title": "How to love",
        "Type": "video",
        "Date": "14 years ago",
        "Platform ID": "2Pdy85P4Lm8",
        "URL": "https://www.youtube.com/watch?v=2Pdy85P4Lm8",
        "Embed (iframe)": "<iframe width=\"560\" height=\"315\" src=\"https://www.youtube.com/embed/2Pdy85P4Lm8\" frameborder=\"0\" allowfullscreen></iframe>"
      },
      {
        "Source": "YouTube",
        "Artist/Channel": "Colin Ward (@colinrfw)",
        "Title": "Castle thing",
        "Type": "video",
        "Date": "14 years ago",
        "Platform ID": "TkNeIghoxrA",
        "URL": "https://www.youtube.com/watch?v=TkNeIghoxrA",
        "Embed (iframe)": "<iframe width=\"560\" height=\"315\" src=\"https://www.youtube.com/embed/TkNeIghoxrA\" frameborder=\"0\" allowfullscreen></iframe>"
      },
      {
        "Source": "YouTube",
        "Artist/Channel": "Luke Thinnes",
        "Title": "Alphabets - Live On Denver Open Media 2011",
        "Type": "video",
        "Date": "2019-10-03",
        "Platform ID": "h_LBkFxlzOc",
        "URL": "https://www.youtube.com/watch?v=h_LBkFxlzOc",
        "Embed (iframe)": "<iframe width=\"560\" height=\"315\" src=\"https://www.youtube.com/embed/h_LBkFxlzOc\" frameborder=\"0\" allowfullscreen></iframe>"
      },
      {
        "Source": "YouTube",
        "Artist/Channel": "B-side Archive (Obscure Music \\u0026 Lost Media)",
        "Title": "alphabets - dec09SCIFI (FULL ALBUM) [2009]",
        "Type": "video",
        "Date": "2022-06-25",
        "Platform ID": "MqUB_DSUvNw",
        "URL": "https://www.youtube.com/watch?v=MqUB_DSUvNw",
        "Embed (iframe)": "<iframe width=\"560\" height=\"315\" src=\"https://www.youtube.com/embed/MqUB_DSUvNw\" frameborder=\"0\" allowfullscreen></iframe>"
      },
      {
        "Source": "SoundCloud",
        "Artist/Channel": "killdby",
        "Title": "Killd By",
        "Type": "profile",
        "Date": null,
        "Platform ID": null,
        "URL": "https://soundcloud.com/killdby",
        "Embed (iframe)": "<iframe width=\"100%\" height=\"166\" scrolling=\"no\" frameborder=\"no\" allow=\"autoplay\" src=\"https://w.soundcloud.com/player/?url=https://soundcloud.com/killdby&color=%23ff5500&auto_play=false&hide_related=false&show_comments=true&show_user=true&show_reposts=false&show_teaser=true\"></iframe>"
      },
      {
        "Source": "SoundCloud",
        "Artist/Channel": "killdby",
        "Title": "Dedication - For Colin Ward",
        "Type": "track",
        "Date": null,
        "Platform ID": "395543691",
        "URL": "https://soundcloud.com/thug-entrancer/dedication-for-colin-ward",
        "Embed (iframe)": "<iframe width=\"100%\" height=\"166\" scrolling=\"no\" frameborder=\"no\" allow=\"autoplay\" src=\"https://w.soundcloud.com/player/?url=https://soundcloud.com/thug-entrancer/dedication-for-colin-ward&color=%23ff5500&auto_play=false&hide_related=false&show_comments=true&show_user=true&show_reposts=false&show_teaser=true\"></iframe>"
      }
    ]
  }
}