{
  "kind": "track",
  "id": "alphabets-bieber-jerboa-03-dream-life-inter-missiles",
  "slug": "alphabets-bieber-jerboa-03-dream-life-inter-missiles",
  "title": "DREAM LIFE inter missiles",
  "preservedTitle": "DREAM LIFE inter missiles",
  "created": "2026-04-20",
  "sensitivity": "public",
  "public_display": true,
  "confidence": "high",
  "release": "releases/alphabets-bieber-jerboa",
  "project": "projects/alphabets",
  "position": 3,
  "credits": [],
  "tags": [
    "bandcamp"
  ],
  "body": "# DREAM LIFE inter missiles\n\nTrack 3 from \"[[releases/alphabets-bieber-jerboa]]\"."
}
