{
  "kind": "track",
  "id": "alphabets-play-soundtrack-10-iiii-iiiiv",
  "slug": "alphabets-play-soundtrack-10-iiii-iiiiv",
  "title": "IIIi-IIIiv",
  "preservedTitle": "IIIi-IIIiv",
  "created": "2026-04-20",
  "sensitivity": "public",
  "public_display": true,
  "confidence": "high",
  "release": "releases/alphabets-play-soundtrack",
  "project": "projects/alphabets",
  "position": 10,
  "credits": [],
  "tags": [
    "bandcamp"
  ],
  "body": "# IIIi-IIIiv\n\nTrack 10 from \"[[releases/alphabets-play-soundtrack]]\"."
}
